zope.viewlet-5.0-py3.9-nspkg.pth
zope/viewlet/README.rst
zope/viewlet/__init__.py
zope/viewlet/communicating-viewlets.rst
zope/viewlet/configure.zcml
zope/viewlet/css_bundle_viewlet.pt
zope/viewlet/css_viewlet.pt
zope/viewlet/directives.rst
zope/viewlet/interfaces.py
zope/viewlet/javascript_bundle_viewlet.pt
zope/viewlet/javascript_viewlet.pt
zope/viewlet/manager.py
zope/viewlet/meta.zcml
zope/viewlet/metaconfigure.py
zope/viewlet/metadirectives.py
zope/viewlet/tests.py
zope/viewlet/viewlet.py
zope.viewlet-5.0.dist-info/LICENSE.txt
zope.viewlet-5.0.dist-info/METADATA
zope.viewlet-5.0.dist-info/WHEEL
zope.viewlet-5.0.dist-info/namespace_packages.txt
zope.viewlet-5.0.dist-info/top_level.txt
zope.viewlet-5.0.dist-info/RECORD
